[{
  "_id": {
    "$oid": "6451a2a7a1c31b01dd3a40b0"
  },
  "Montadora": "Chevrolet",
  "País": "EUA"
},{
  "_id": {
    "$oid": "6451a2a7a1c31b01dd3a40b1"
  },
  "Montadora": "Volkswagen",
  "País": "Alemanhã"
},{
  "_id": {
    "$oid": "6451a2a7a1c31b01dd3a40b2"
  },
  "Montadora": "Renault",
  "País": "França"
},{
  "_id": {
    "$oid": "6451a2a7a1c31b01dd3a40b3"
  },
  "Montadora": "Ford",
  "País": "EUA"
},{
  "_id": {
    "$oid": "6451a2a7a1c31b01dd3a40b4"
  },
  "Montadora": "Honda",
  "País": "Japão"
}]